TextVectorizer/Vectorizer.py
TextVectorizer/__init__.py
TextVectorizer/algorithm.py
TextVectorizer-0.1.0.dist-info/LICENSE
TextVectorizer-0.1.0.dist-info/METADATA
TextVectorizer-0.1.0.dist-info/WHEEL
TextVectorizer-0.1.0.dist-info/top_level.txt
TextVectorizer-0.1.0.dist-info/RECORD
