Metadata-Version: 2.1
Name: TextVectorizer
Version: 0.1.0
Summary: Feature Engineering for Textual Data
Home-page: https://github.com/itsshavar/TextVectorizer
Author: Shashi Tripathi, Rahul Kumar Yadav
Author-email: shashi.123.prakash@gmail.com,rahulkryadav93@gmail.com
License: UNKNOWN
Platform: UNKNOWN
Requires-Dist: spacy
Requires-Dist: spacy-transformers
